monostyle/__init__.py
monostyle/__main__.py
monostyle/autofix.py
monostyle/capitalization.py
monostyle/char.py
monostyle/code_style.py
monostyle/config.py
monostyle/git_inter.py
monostyle/image.py
monostyle/listsearch.py
monostyle/markup.py
monostyle/markup2.py
monostyle/monitor.py
monostyle/natural.py
monostyle/punctuation.py
monostyle/reflow.py
monostyle/spelling.py
monostyle/svn_inter.py
monostyle/update_lexicon.py
monostyle/data/avoid.json
monostyle/data/blender.json
monostyle/data/char_catalog.json
monostyle/data/common_abbr.json
monostyle/data/config.json
monostyle/data/dev.json
monostyle/data/indefinite_article.json
monostyle/data/irregular_participle.json
monostyle/data/part_of_speech.json
monostyle/data/simplify.json
monostyle/rst_parser/__init__.py
monostyle/rst_parser/core.py
monostyle/rst_parser/environment.py
monostyle/rst_parser/hunk_post_parser.py
monostyle/rst_parser/rst_node.py
monostyle/rst_parser/rst_parser_spec.txt
monostyle/rst_parser/walker.py
monostyle/util/__init__.py
monostyle/util/char_catalog.py
monostyle/util/editor.py
monostyle/util/file_opener.py
monostyle/util/fragment.py
monostyle/util/lexicon.py
monostyle/util/monostyle_io.py
monostyle/util/nodes.py
monostyle/util/part_of_speech.py
monostyle/util/porter_stemmer.py
monostyle/util/report.py
monostyle/util/segmenter.py
monostyle-0.4.1.dist-info/LICENSE
monostyle-0.4.1.dist-info/METADATA
monostyle-0.4.1.dist-info/WHEEL
monostyle-0.4.1.dist-info/entry_points.txt
monostyle-0.4.1.dist-info/top_level.txt
monostyle-0.4.1.dist-info/RECORD
