Metadata-Version: 2.1
Name: monostyle
Version: 0.4.1
Summary: Tools for style checking and linting
Home-page: https://github.com/tobiasHeinke/monostyle
Author: Tobias Heinke
Author-email: tobias.heinke@outlook.com
License: GPLv3+
Download-URL: https://pypi.org/project/monostyle/
Project-URL: Code, https://github.com/tobiasHeinke/monostyle
Project-URL: Issue tracker, https://github.com/tobiasHeinke/monostyle/issues
Keywords: linter,rst,documentation,style guide
Platform: any
Classifier: Development Status :: 5 - Production/Stable
Classifier: Environment :: Console
Classifier: Intended Audience :: Developers
Classifier: Intended Audience :: Education
Classifier: Intended Audience :: System Administrators
Classifier: Programming Language :: Python :: 3
Classifier: License :: OSI Approved :: GNU General Public License v3 or later (GPLv3+)
Classifier: Operating System :: OS Independent
Classifier: Topic :: Documentation
Classifier: Topic :: Software Development
Classifier: Topic :: Software Development :: Documentation
Classifier: Topic :: Text Processing
Classifier: Topic :: Text Processing :: Markup
Classifier: Topic :: Text Editors
Classifier: Topic :: Text Editors :: Documentation
Classifier: Topic :: Text Editors :: Text Processing
Requires-Python: >=3.6
License-File: LICENSE
